pi_inference_worker/__init__.py
pi_inference_worker/env.py
pi_inference_worker/server.py
pi_inference_worker-0.1.0.dist-info/METADATA
pi_inference_worker-0.1.0.dist-info/WHEEL
pi_inference_worker-0.1.0.dist-info/entry_points.txt
pi_inference_worker-0.1.0.dist-info/RECORD
