Metadata-Version: 2.4
Name: pi-inference-worker
Version: 0.1.0
Summary: prime inference worker
Author-email: Jackmin801 <ongjackm@gmail.com>
License: MIT
Requires-Python: <3.13,>=3.11
Requires-Dist: datasets
Requires-Dist: fastapi[standard]
Requires-Dist: pyarrow
Requires-Dist: setuptools
Requires-Dist: shardcast>=0.1.8
Requires-Dist: toploc>=0.1.6
Requires-Dist: torch
Requires-Dist: transformers
Requires-Dist: uvicorn[standard]
Requires-Dist: vllm
Provides-Extra: gcp
Requires-Dist: google-cloud-storage; extra == 'gcp'
